core_get/__init__.py
core_get/main.py
core_get/actions/__init__.py
core_get/actions/action.py
core_get/actions/action_executor.py
core_get/actions/execute.py
core_get/actions/module.py
core_get/actions/init/__init__.py
core_get/actions/init/init.py
core_get/actions/init/init_options.py
core_get/actions/install/__init__.py
core_get/actions/install/install.py
core_get/actions/install/install_options.py
core_get/actions/login/__init__.py
core_get/actions/login/login.py
core_get/actions/login/login_options.py
core_get/actions/package/__init__.py
core_get/actions/package/package.py
core_get/actions/package/package_options.py
core_get/actions/publish/__init__.py
core_get/actions/publish/publish.py
core_get/actions/publish/publish_options.py
core_get/actions/remove/__init__.py
core_get/actions/remove/remove.py
core_get/actions/remove/remove_options.py
core_get/actions/test/__init__.py
core_get/actions/test/test.py
core_get/actions/test/test_options.py
core_get/actions/yank/__init__.py
core_get/actions/yank/yank.py
core_get/actions/yank/yank_options.py
core_get/catalog/__init__.py
core_get/catalog/catalog_service.py
core_get/catalog/download_status_interface.py
core_get/catalog/network_service.py
core_get/cli/__init__.py
core_get/cli/cli_main.py
core_get/cli/module.py
core_get/cli/parse/__init__.py
core_get/cli/parse/composite_parser.py
core_get/cli/parse/main_parser.py
core_get/cli/parse/parse.py
core_get/cli/parse/parser.py
core_get/cli/parse/parser_selector.py
core_get/cli/parse/options_parsers/__init__.py
core_get/cli/parse/options_parsers/common_options_parser.py
core_get/cli/parse/options_parsers/init_options_parser.py
core_get/cli/parse/options_parsers/install_options_parser.py
core_get/cli/parse/options_parsers/login_options_parser.py
core_get/cli/parse/options_parsers/package_options_parser.py
core_get/cli/parse/options_parsers/publish_options_parser.py
core_get/cli/parse/options_parsers/remove_options_parser.py
core_get-0.1.8.dist-info/LICENSE.md
core_get-0.1.8.dist-info/METADATA
core_get-0.1.8.dist-info/WHEEL
core_get-0.1.8.dist-info/top_level.txt
core_get-0.1.8.dist-info/RECORD
