Metadata-Version: 2.1
Name: core-get
Version: 0.1.8
Summary: Client for the core-get package sharing system
Home-page: https://github.com/core-get/core-get
Author: Oskar Holstensson
Author-email: oskar@holstensson.se
License: MIT
Platform: UNKNOWN
Requires-Dist: tomlkit (~=0.7.0)
Requires-Dist: injector (~=0.18.3)
Requires-Dist: appdirs (~=1.4.4)
Requires-Dist: semver (~=2.13.0)
Requires-Dist: requests (~=2.25.0)
Requires-Dist: vunit-hdl (~=4.4.0)
